jobautomate/__init__.py
jobautomate/__main__.py
jobautomate/commandline.py
jobautomate-0.18.10.dist-info/DESCRIPTION.rst
jobautomate-0.18.10.dist-info/METADATA
jobautomate-0.18.10.dist-info/RECORD
jobautomate-0.18.10.dist-info/WHEEL
jobautomate-0.18.10.dist-info/entry_points.txt
jobautomate-0.18.10.dist-info/metadata.json
jobautomate-0.18.10.dist-info/top_level.txt
