Metadata-Version: 2.0
Name: jobautomate
Version: 0.18.10
Summary: Automate a job search with Indeed
Home-page: https://github.com/mandeep/Job-Automate
Author: Mandeep Bhutani
Author-email: UNKNOWN
License: GPLv3+
Platform: UNKNOWN
Classifier: Development Status :: 3 - Alpha
Classifier: License :: OSI Approved :: GNU General Public License v3 or later (GPLv3+)
Classifier: Programming Language :: Python :: 3.3
Classifier: Programming Language :: Python :: 3.4
Classifier: Programming Language :: Python :: 3.5
Requires-Dist: click (==6.6)
Requires-Dist: indeed (==0.0.4)
Requires-Dist: selenium (==2.53.6)
Requires-Dist: xvfbwrapper (==0.2.8)
